django_unused_media/__init__.py
django_unused_media/cleanup.py
django_unused_media/models.py
django_unused_media/remove.py
django_unused_media/utils.py
django_unused_media/management/__init__.py
django_unused_media/management/commands/__init__.py
django_unused_media/management/commands/cleanup_unused_media.py
tests/__init__.py
tests/base.py
tests/models.py
tests/runtests.py
tests/settings.py
tests/test_cleanup.py
tests/test_management.py
django_unused_media-0.2.2.dist-info/LICENSE
django_unused_media-0.2.2.dist-info/METADATA
django_unused_media-0.2.2.dist-info/WHEEL
django_unused_media-0.2.2.dist-info/entry_points.txt
django_unused_media-0.2.2.dist-info/top_level.txt
django_unused_media-0.2.2.dist-info/RECORD
