Metadata-Version: 2.1
Name: django-unused-media
Version: 0.2.2
Summary: Delete unused media files from Django project
Home-page: https://github.com/akolpakov/django-unused-media
Author: Andrey Kolpakov
Author-email: aakolpakov@gmail.com
License: MIT
Keywords: python django unused media remove delete
Platform: UNKNOWN
Classifier: Development Status :: 4 - Beta
Classifier: Intended Audience :: Developers
Classifier: License :: OSI Approved :: MIT License
Classifier: Natural Language :: English
Classifier: Operating System :: Unix
Classifier: Programming Language :: Python :: 2.7
Classifier: Programming Language :: Python :: 3.3
Classifier: Programming Language :: Python :: 3.4
Classifier: Programming Language :: Python :: 3.5
Classifier: Programming Language :: Python :: Implementation :: PyPy
Classifier: Operating System :: OS Independent
Provides-Extra: tests
